recipe_app/main.py
recipe_app/models.py
recipe_app/services.py
recipe_app/storage.py
recipe_app/ui.py
recipe_app-0.1.0.dist-info/METADATA
recipe_app-0.1.0.dist-info/WHEEL
recipe_app-0.1.0.dist-info/entry_points.txt
recipe_app-0.1.0.dist-info/RECORD
