Metadata-Version: 2.4
Name: recipe_app
Version: 0.1.0
Summary: A recipe management CLI application
Author-email: Mike Curtin <michaelcurtin31@gmail.com>
License: MIT
Classifier: License :: OSI Approved :: MIT License
Classifier: Programming Language :: Python :: 3
Requires-Python: >=3.13
Requires-Dist: pydantic>=2.12
Requires-Dist: rich>=14.2.0
Requires-Dist: typer>=0.21.1
